chai_config/__init__.py
chai_config/config.py
chai_model_config-0.1.0.dist-info/METADATA
chai_model_config-0.1.0.dist-info/WHEEL
chai_model_config-0.1.0.dist-info/top_level.txt
chai_model_config-0.1.0.dist-info/RECORD
